foxwebsite/__init__.py
foxwebsite/framework.py
foxwebsite-0.1.1.dist-info/METADATA
foxwebsite-0.1.1.dist-info/WHEEL
foxwebsite-0.1.1.dist-info/top_level.txt
foxwebsite-0.1.1.dist-info/RECORD
