Metadata-Version: 2.1
Name: foxwebsite
Version: 0.1.1
Summary: A sample Python package
Author-email: shunianssy <sbox520@163.com>
License: MPL-2.0
Project-URL: Homepage, https://github.com/shunianssy/foxwebsite
Project-URL: Repository, https://github.com/shunianssy/foxwebsite.git
Classifier: License :: OSI Approved :: Mozilla Public License 2.0 (MPL 2.0)
Classifier: Programming Language :: Python
Classifier: Programming Language :: Python :: 3
Requires-Python: >=3.8
Requires-Dist: requests>=2.25.0
